Compiled from "ReorderingExample.java"
public class com.jangz.concurrent.thread.reorder.ReorderingExample {
  public com.jangz.concurrent.thread.reorder.ReorderingExample();
    Code:
       0: aload_0
       1: invokespecial #1                  // Method java/lang/Object."<init>":()V
       4: return

  public static void main(java.lang.String[]);
    Code:
       0: iconst_1
       1: istore_1
       2: iconst_2
       3: istore_1
       4: iconst_0
       5: iconst_0
       6: idiv
       7: istore_2
       8: getstatic     #2                  // Field java/lang/System.out:Ljava/io/PrintStream;
      11: new           #3                  // class java/lang/StringBuilder
      14: dup
      15: invokespecial #4                  // Method java/lang/StringBuilder."<init>":()V
      18: ldc           #5                  // String x =
      20: invokevirtual #6                  // Method java/lang/StringBuilder.append:(Ljava/lang/String;)Ljava/lang/StringBuilder;
      23: iload_1
      24: invokevirtual #7                  // Method java/lang/StringBuilder.append:(I)Ljava/lang/StringBuilder;
      27: invokevirtual #8                  // Method java/lang/StringBuilder.toString:()Ljava/lang/String;
      30: invokevirtual #9                  // Method java/io/PrintStream.println:(Ljava/lang/String;)V
      33: goto          95
      36: astore_3
      37: getstatic     #2                  // Field java/lang/System.out:Ljava/io/PrintStream;
      40: new           #3                  // class java/lang/StringBuilder
      43: dup
      44: invokespecial #4                  // Method java/lang/StringBuilder."<init>":()V
      47: ldc           #5                  // String x =
      49: invokevirtual #6                  // Method java/lang/StringBuilder.append:(Ljava/lang/String;)Ljava/lang/StringBuilder;
      52: iload_1
      53: invokevirtual #7                  // Method java/lang/StringBuilder.append:(I)Ljava/lang/StringBuilder;
      56: invokevirtual #8                  // Method java/lang/StringBuilder.toString:()Ljava/lang/String;
      59: invokevirtual #9                  // Method java/io/PrintStream.println:(Ljava/lang/String;)V
      62: goto          95
      65: astore        4
      67: getstatic     #2                  // Field java/lang/System.out:Ljava/io/PrintStream;
      70: new           #3                  // class java/lang/StringBuilder
      73: dup
      74: invokespecial #4                  // Method java/lang/StringBuilder."<init>":()V
      77: ldc           #5                  // String x =
      79: invokevirtual #6                  // Method java/lang/StringBuilder.append:(Ljava/lang/String;)Ljava/lang/StringBuilder;
      82: iload_1
      83: invokevirtual #7                  // Method java/lang/StringBuilder.append:(I)Ljava/lang/StringBuilder;
      86: invokevirtual #8                  // Method java/lang/StringBuilder.toString:()Ljava/lang/String;
      89: invokevirtual #9                  // Method java/io/PrintStream.println:(Ljava/lang/String;)V
      92: aload         4
      94: athrow
      95: return
    Exception table:
       from    to  target type
           2     8    36   Class java/lang/Exception
           2     8    65   any
          65    67    65   any
}
